odoo/addons/analytic_tag_dimension_purchase_warning/README.rst
odoo/addons/analytic_tag_dimension_purchase_warning/__init__.py
odoo/addons/analytic_tag_dimension_purchase_warning/__manifest__.py
odoo/addons/analytic_tag_dimension_purchase_warning/models/__init__.py
odoo/addons/analytic_tag_dimension_purchase_warning/models/purchase.py
odoo11_addon_analytic_tag_dimension_purchase_warning-11.0.1.0.0.dist-info/DESCRIPTION.rst
odoo11_addon_analytic_tag_dimension_purchase_warning-11.0.1.0.0.dist-info/METADATA
odoo11_addon_analytic_tag_dimension_purchase_warning-11.0.1.0.0.dist-info/RECORD
odoo11_addon_analytic_tag_dimension_purchase_warning-11.0.1.0.0.dist-info/WHEEL
odoo11_addon_analytic_tag_dimension_purchase_warning-11.0.1.0.0.dist-info/metadata.json
odoo11_addon_analytic_tag_dimension_purchase_warning-11.0.1.0.0.dist-info/top_level.txt
